<?xml version="1.0" encoding="UTF-8"?>
<con:soapui-project id="a6bf05fe-3817-4ebc-aee5-3dfbee3dee80" created="3.7.0" activeEnvironment="Default environment" name="REST Project 2" resourceRoot="" updated="3.7.0 2021-03-30T19:14:40Z" xmlns:con="http://eviware.com/soapui/config">
  <con:settings/>
  <con:interface xsi:type="con:RestService" id="54027c30-5a0e-4517-844d-527434b1738d" wadlVersion="http://wadl.dev.java.net/2009/02" name="https://petstore.swagger.io" type="rest" xmlns:xsi="http://www.w3.org/2001/XMLSchema-instance">
    <con:settings/>
    <con:definitionCache type="TEXT" rootPart=""/>
    <con:endpoints>
      <con:endpoint>https://petstore.swagger.io</con:endpoint>
    </con:endpoints>
    <con:resource name="User" path="/v2/user" id="42cf6ed8-5d7f-4e8c-8fb3-b7daf32144b2">
      <con:settings/>
      <con:parameters>
        <con:parameter>
          <con:name>username</con:name>
          <con:style>QUERY</con:style>
        </con:parameter>
      </con:parameters>
      <con:resource name="login" path="login" id="08dc1c4f-df53-4454-b5c5-84d0f30d438a">
        <con:settings/>
        <con:parameters>
          <con:parameter>
            <con:name>username</con:name>
            <con:style>TEMPLATE</con:style>
          </con:parameter>
        </con:parameters>
        <con:method name="Method 1" id="4532ad27-b034-4de9-acd8-b2d789a6a243" method="GET">
          <con:settings/>
          <con:parameters/>
          <con:representation type="RESPONSE">
            <con:mediaType>application/json</con:mediaType>
            <con:status>200</con:status>
            <con:params/>
            <con:element xmlns:log="https://petstore.swagger.io/v2/user/login">log:Response</con:element>
          </con:representation>
          <con:representation type="FAULT">
            <con:mediaType>application/xml</con:mediaType>
            <con:status>405 404</con:status>
            <con:params/>
            <con:element>apiResponse</con:element>
          </con:representation>
          <con:representation type="FAULT">
            <con:mediaType>application/json</con:mediaType>
            <con:status>404</con:status>
            <con:params/>
            <con:element xmlns:log="https://petstore.swagger.io/v2/user/login">log:Fault</con:element>
          </con:representation>
          <con:representation type="RESPONSE">
            <con:mediaType>text/html</con:mediaType>
            <con:status>200</con:status>
            <con:params/>
            <con:element>html</con:element>
          </con:representation>
          <con:request name="get login method" id="11a082cf-47fc-4f81-8e51-3eb1bac59459" mediaType="application/json">
            <con:settings>
              <con:setting id="com.eviware.soapui.impl.wsdl.WsdlRequest@request-headers">&lt;xml-fragment/></con:setting>
            </con:settings>
            <con:endpoint>https://petstore.swagger.io</con:endpoint>
            <con:request/>
            <con:originalUri>https://petstore.swagger.io/v2/user/login</con:originalUri>
            <con:credentials>
              <con:authType>No Authorization</con:authType>
            </con:credentials>
            <con:jmsConfig JMSDeliveryMode="PERSISTENT"/>
            <con:parameters/>
            <con:parameterOrder>
              <con:entry>username</con:entry>
            </con:parameterOrder>
          </con:request>
        </con:method>
      </con:resource>
      <con:resource name="logout" path="logout" id="cff9cc3b-3660-4f21-b1e4-4f4624739dc1">
        <con:settings/>
        <con:parameters>
          <con:parameter>
            <con:name>username</con:name>
            <con:value/>
            <con:style>TEMPLATE</con:style>
            <con:default/>
          </con:parameter>
        </con:parameters>
        <con:method name="Method 1" id="ab3993b2-b3e5-47b6-848f-a4ece0739977" method="GET">
          <con:settings/>
          <con:parameters/>
          <con:representation type="RESPONSE">
            <con:mediaType>application/json</con:mediaType>
            <con:status>200</con:status>
            <con:params/>
            <con:element xmlns:log="https://petstore.swagger.io/v2/user/logout">log:Response</con:element>
          </con:representation>
          <con:representation type="FAULT">
            <con:mediaType>application/xml</con:mediaType>
            <con:status>405</con:status>
            <con:params/>
            <con:element>apiResponse</con:element>
          </con:representation>
          <con:request name="get logout method" id="6b96fb6a-2d85-4e20-9118-736e22553662" mediaType="application/json">
            <con:settings>
              <con:setting id="com.eviware.soapui.impl.wsdl.WsdlRequest@request-headers">&lt;xml-fragment/></con:setting>
            </con:settings>
            <con:endpoint>https://petstore.swagger.io</con:endpoint>
            <con:request/>
            <con:originalUri>https://petstore.swagger.io/v2/user/logout</con:originalUri>
            <con:credentials>
              <con:authType>No Authorization</con:authType>
            </con:credentials>
            <con:jmsConfig JMSDeliveryMode="PERSISTENT"/>
            <con:parameters>
              <con:entry key="username" value=""/>
            </con:parameters>
            <con:parameterOrder>
              <con:entry>username</con:entry>
            </con:parameterOrder>
          </con:request>
        </con:method>
      </con:resource>
      <con:resource name="{username}" path="/{username}" id="62130826-0fdf-4b1a-81ff-9090bf39f6d8">
        <con:settings/>
        <con:parameters>
          <con:parameter required="true">
            <con:name>username</con:name>
            <con:value>username</con:value>
            <con:style>TEMPLATE</con:style>
            <con:default>username</con:default>
          </con:parameter>
        </con:parameters>
        <con:method name="Method 1" id="76111bda-a278-413d-a332-c7428c9d5907" method="PUT">
          <con:settings/>
          <con:parameters/>
          <con:representation type="RESPONSE">
            <con:mediaType>application/json</con:mediaType>
            <con:status>200</con:status>
            <con:params/>
            <con:element xmlns:user="https://petstore.swagger.io/v2/user/username">user:Response</con:element>
          </con:representation>
          <con:representation type="REQUEST">
            <con:mediaType>application/json</con:mediaType>
            <con:params/>
          </con:representation>
          <con:representation type="FAULT">
            <con:mediaType>application/xml</con:mediaType>
            <con:status>404 405</con:status>
            <con:params/>
            <con:element>apiResponse</con:element>
          </con:representation>
          <con:representation type="FAULT">
            <con:mediaType>text/html</con:mediaType>
            <con:status>405</con:status>
            <con:params/>
            <con:element>html</con:element>
          </con:representation>
        </con:method>
        <con:method name="Method 2" id="86434d6e-0e0f-4439-98c6-4886fa1780fd" method="DELETE">
          <con:settings/>
          <con:parameters/>
          <con:representation type="REQUEST">
            <con:mediaType>application/json</con:mediaType>
            <con:params/>
          </con:representation>
          <con:representation type="FAULT">
            <con:mediaType xsi:nil="true"/>
            <con:status>404</con:status>
            <con:params/>
            <con:element>data</con:element>
          </con:representation>
          <con:representation type="FAULT">
            <con:mediaType>application/xml</con:mediaType>
            <con:status>405</con:status>
            <con:params/>
            <con:element>apiResponse</con:element>
          </con:representation>
          <con:representation type="RESPONSE">
            <con:mediaType>application/json</con:mediaType>
            <con:status>200</con:status>
            <con:params/>
            <con:element xmlns:user="https://petstore.swagger.io/v2/user/username">user:Response</con:element>
          </con:representation>
          <con:request name="delete method" id="352a4d42-1180-434b-9c58-33fbc0f3597c" mediaType="application/json" postQueryString="false">
            <con:settings>
              <con:setting id="com.eviware.soapui.impl.wsdl.WsdlRequest@request-headers">&lt;xml-fragment/></con:setting>
            </con:settings>
            <con:endpoint>https://petstore.swagger.io</con:endpoint>
            <con:request/>
            <con:originalUri>https://petstore.swagger.io/v2/user/username</con:originalUri>
            <con:credentials>
              <con:authType>No Authorization</con:authType>
            </con:credentials>
            <con:jmsConfig JMSDeliveryMode="PERSISTENT"/>
            <con:parameters>
              <con:entry key="username" value=""/>
            </con:parameters>
          </con:request>
        </con:method>
        <con:method name="Method 3" id="7081f6c8-7cd3-4d4d-b0d8-910478c217f8" method="GET">
          <con:settings/>
          <con:parameters/>
          <con:representation type="RESPONSE">
            <con:mediaType>application/json</con:mediaType>
            <con:status>200</con:status>
            <con:params/>
            <con:element xmlns:giri="https://petstore.swagger.io/v2/user/giri">giri:Response</con:element>
          </con:representation>
          <con:request name="get method" id="603d1cd3-45e6-40e4-b774-4b05c8af5fb3" mediaType="application/json">
            <con:settings/>
            <con:endpoint>https://petstore.swagger.io</con:endpoint>
            <con:request/>
            <con:credentials>
              <con:authType>No Authorization</con:authType>
            </con:credentials>
            <con:jmsConfig JMSDeliveryMode="PERSISTENT"/>
            <con:parameters/>
          </con:request>
        </con:method>
        <con:method name="Method 4" id="42eb00a0-0321-4c11-b9a2-cfe149307041" method="PUT">
          <con:settings/>
          <con:parameters/>
          <con:representation type="RESPONSE">
            <con:mediaType>application/json</con:mediaType>
            <con:status>200</con:status>
            <con:params/>
            <con:element xmlns:user="https://petstore.swagger.io/v2/user/username">user:Response</con:element>
          </con:representation>
          <con:representation type="REQUEST">
            <con:mediaType>application/json</con:mediaType>
            <con:params/>
          </con:representation>
          <con:request name="put method" id="6d1b006e-993c-494a-922a-81c39bc41aa8" mediaType="application/json" postQueryString="false">
            <con:settings>
              <con:setting id="com.eviware.soapui.impl.wsdl.WsdlRequest@request-headers">&lt;xml-fragment/></con:setting>
            </con:settings>
            <con:endpoint>https://petstore.swagger.io</con:endpoint>
            <con:request>{
  "id": 0,
  "username": "string",
  "firstName": "string",
  "lastName": "string",
  "email": "string",
  "password": "string",
  "phone": "string",
  "userStatus": 0
}</con:request>
            <con:originalUri>https://petstore.swagger.io/v2/user/username</con:originalUri>
            <con:credentials>
              <con:authType>No Authorization</con:authType>
            </con:credentials>
            <con:jmsConfig JMSDeliveryMode="PERSISTENT"/>
            <con:parameters/>
          </con:request>
        </con:method>
      </con:resource>
      <con:method name="User" id="d2b90866-074c-4934-b413-778814a63cb9" method="POST">
        <con:settings/>
        <con:parameters/>
        <con:representation type="REQUEST">
          <con:mediaType>application/json</con:mediaType>
          <con:params/>
        </con:representation>
        <con:representation type="RESPONSE">
          <con:mediaType>application/json</con:mediaType>
          <con:status>200</con:status>
          <con:params/>
          <con:element xmlns:user="https://petstore.swagger.io/v2/user">user:Response</con:element>
        </con:representation>
        <con:representation type="FAULT">
          <con:mediaType>text/html</con:mediaType>
          <con:status>405</con:status>
          <con:params/>
          <con:element>html</con:element>
        </con:representation>
        <con:request name="Request 1" id="340b05c4-0c85-4ce5-ab62-172780faffd7" mediaType="application/json" postQueryString="false">
          <con:settings>
            <con:setting id="com.eviware.soapui.impl.wsdl.WsdlRequest@request-headers">&lt;xml-fragment/></con:setting>
          </con:settings>
          <con:endpoint>https://petstore.swagger.io</con:endpoint>
          <con:request>{
  "id": 0,
  "username": "string",
  "firstName": "string",
  "lastName": "string",
  "email": "string",
  "password": "string",
  "phone": "string",
  "userStatus": 0
}</con:request>
          <con:originalUri>https://petstore.swagger.io/v2/user</con:originalUri>
          <con:credentials>
            <con:authType>No Authorization</con:authType>
          </con:credentials>
          <con:jmsConfig JMSDeliveryMode="PERSISTENT"/>
          <con:parameters/>
        </con:request>
      </con:method>
    </con:resource>
  </con:interface>
  <con:testSuite id="6be124ca-6c59-4569-8526-80be2dadd83f" name="https://petstore.swagger.io Test Suite">
    <con:settings/>
    <con:savedRecentRuns>1</con:savedRecentRuns>
    <con:runType>SEQUENTIAL</con:runType>
    <con:testCase id="5b9b9451-f5f0-4d3e-b6e9-fd2dfa495182" discardOkResults="false" failOnError="true" failTestCaseOnErrors="true" keepSession="false" name="https://petstore.swagger.io Test Case 1" searchProperties="true" timeout="0">
      <con:settings/>
      <con:savedRecentRuns>1</con:savedRecentRuns>
      <con:testStep type="datasource" name="Data Source" id="4f3e129b-d2b7-492f-8c46-8a66233dece3">
        <con:settings/>
        <con:config xsi:type="con:DataSourceStep" xmlns:xsi="http://www.w3.org/2001/XMLSchema-instance">
          <con:dataSource type="Excel">
            <con:configuration>
              <file>E:/Book1.xlsx</file>
              <worksheet>sheet1</worksheet>
              <cell>a2</cell>
              <ignoreEmpty>false</ignoreEmpty>
              <evaluateFormulas>false</evaluateFormulas>
            </con:configuration>
          </con:dataSource>
          <con:shared>true</con:shared>
          <con:restartShared>true</con:restartShared>
          <con:property>username</con:property>
          <con:property>password</con:property>
          <con:property>firstname</con:property>
          <con:property>lastname</con:property>
          <con:property>phoennum</con:property>
          <con:property>email</con:property>
          <con:property>validnum</con:property>
          <con:restartOnRun>true</con:restartOnRun>
        </con:config>
      </con:testStep>
      <con:testStep type="restrequest" name="POST_API" id="a24c9ed9-6510-4488-a6be-3d3f1c3ed18a">
        <con:settings/>
        <con:config service="https://petstore.swagger.io" resourcePath="/v2/user" methodName="User" xsi:type="con:RestRequestStep" xmlns:xsi="http://www.w3.org/2001/XMLSchema-instance">
          <con:restRequest name="POST_API" id="340b05c4-0c85-4ce5-ab62-172780faffd7" mediaType="application/json" postQueryString="false">
            <con:settings>
              <con:setting id="com.eviware.soapui.impl.wsdl.WsdlRequest@request-headers">&lt;xml-fragment/></con:setting>
            </con:settings>
            <con:endpoint>https://petstore.swagger.io</con:endpoint>
            <con:request>{
  "id": 0,
  "username": "${Data Source#username}",
  "firstName": "${Data Source#firstname}",
  "lastName": "${Data Source#lastname}",
  "email": "${Data Source#email}",
  "password": "${Data Source#password}",
  "phone": "${Data Source#phoennum}",
  "userStatus": 0
}</con:request>
            <con:originalUri>https://petstore.swagger.io/v2/user</con:originalUri>
            <con:credentials>
              <con:selectedAuthProfile>No Authorization</con:selectedAuthProfile>
              <con:authType>No Authorization</con:authType>
            </con:credentials>
            <con:jmsConfig JMSDeliveryMode="PERSISTENT"/>
            <con:parameters>
              <con:entry key="username" value="${Data Source#username}"/>
            </con:parameters>
          </con:restRequest>
        </con:config>
      </con:testStep>
      <con:testStep type="transfer" name="Property Transfer" id="7cebd24a-6760-4112-a3d3-352d36a3f0d6">
        <con:settings/>
        <con:config xsi:type="con:PropertyTransfersStep" xmlns:xsi="http://www.w3.org/2001/XMLSchema-instance">
          <con:transfers setNullOnMissingSource="true" transferTextContent="true" failOnError="true" ignoreEmpty="false" transferToAll="false" entitize="false" transferChildNodes="false">
            <con:name>ID</con:name>
            <con:sourceType>Response</con:sourceType>
            <con:sourceStep>POST_API</con:sourceStep>
            <con:sourcePath>$['code']</con:sourcePath>
            <con:targetType>Username</con:targetType>
            <con:targetStep>get login_API</con:targetStep>
            <con:targetPath/>
            <con:type>JSONPATH</con:type>
            <con:upgraded>true</con:upgraded>
          </con:transfers>
          <con:transfers setNullOnMissingSource="true" transferTextContent="true" failOnError="true" ignoreEmpty="false" transferToAll="false" entitize="false" transferChildNodes="false">
            <con:name>response</con:name>
            <con:sourceStep>POST_API</con:sourceStep>
            <con:targetStep>get login_API</con:targetStep>
            <con:upgraded>true</con:upgraded>
          </con:transfers>
        </con:config>
      </con:testStep>
      <con:testStep type="restrequest" name="get login_API" id="cb5c34f1-8edf-430c-92f9-870fc943a6d2">
        <con:settings/>
        <con:config service="https://petstore.swagger.io" resourcePath="/v2/user/login" methodName="Method 1" xsi:type="con:RestRequestStep" xmlns:xsi="http://www.w3.org/2001/XMLSchema-instance">
          <con:restRequest name="get login_API" id="11a082cf-47fc-4f81-8e51-3eb1bac59459" mediaType="application/json">
            <con:settings>
              <con:setting id="com.eviware.soapui.impl.wsdl.WsdlRequest@request-headers">&lt;xml-fragment/></con:setting>
            </con:settings>
            <con:endpoint>https://petstore.swagger.io</con:endpoint>
            <con:request/>
            <con:originalUri>https://petstore.swagger.io/v2/user/login</con:originalUri>
            <con:assertion type="MessageContentAssertion" id="3a5fbf93-f8de-471b-9818-3c03219701b6" name="Message Content Assertion">
              <con:configuration xsi:type="con:MessageContentAssertion">
                <con:elements>
                  <con:xpath>//apiResponse[1]/message[1]</con:xpath>
                  <con:element>message</con:element>
                  <con:type xsi:nil="true"/>
                  <con:operator>exists</con:operator>
                  <con:enabled>true</con:enabled>
                  <con:expectedValue>null for uri: http://petstore.swagger.io/v2/login</con:expectedValue>
                  <con:hasValue>false</con:hasValue>
                  <con:numberType>false</con:numberType>
                </con:elements>
                <con:elements>
                  <con:xpath>//apiResponse[1]/type[1]</con:xpath>
                  <con:element>type</con:element>
                  <con:type xsi:nil="true"/>
                  <con:operator>=</con:operator>
                  <con:enabled>true</con:enabled>
                  <con:expectedValue>unknown</con:expectedValue>
                  <con:hasValue>false</con:hasValue>
                  <con:numberType>false</con:numberType>
                </con:elements>
                <con:originalMessage><![CDATA[<apiResponse>
   <message>null for uri: http://petstore.swagger.io/v2/login</message>
   <type>unknown</type>
</apiResponse>]]></con:originalMessage>
              </con:configuration>
            </con:assertion>
            <con:credentials>
              <con:username>200</con:username>
              <con:selectedAuthProfile>No Authorization</con:selectedAuthProfile>
              <con:authType>No Authorization</con:authType>
            </con:credentials>
            <con:jmsConfig JMSDeliveryMode="PERSISTENT"/>
            <con:parameters>
              <con:entry key="username" value="${Data Source#username}"/>
            </con:parameters>
            <con:parameterOrder>
              <con:entry>username</con:entry>
            </con:parameterOrder>
          </con:restRequest>
        </con:config>
      </con:testStep>
      <con:testStep type="restrequest" name="get logou_API" id="5d4ec8bb-31dd-4700-83b4-cd0a8378ae0a">
        <con:settings/>
        <con:config service="https://petstore.swagger.io" resourcePath="/v2/user/login" methodName="Method 1" xsi:type="con:RestRequestStep" xmlns:xsi="http://www.w3.org/2001/XMLSchema-instance">
          <con:restRequest name="get logou_API" id="6b96fb6a-2d85-4e20-9118-736e22553662" mediaType="application/json">
            <con:settings>
              <con:setting id="com.eviware.soapui.impl.wsdl.WsdlRequest@request-headers">&lt;xml-fragment/></con:setting>
            </con:settings>
            <con:endpoint>https://petstore.swagger.io</con:endpoint>
            <con:request/>
            <con:originalUri>https://petstore.swagger.io/v2/user/logout</con:originalUri>
            <con:credentials>
              <con:selectedAuthProfile>No Authorization</con:selectedAuthProfile>
              <con:authType>No Authorization</con:authType>
            </con:credentials>
            <con:jmsConfig JMSDeliveryMode="PERSISTENT"/>
            <con:parameters>
              <con:entry key="username" value="${Data Source#username}"/>
            </con:parameters>
            <con:parameterOrder>
              <con:entry>username</con:entry>
            </con:parameterOrder>
          </con:restRequest>
        </con:config>
      </con:testStep>
      <con:testStep type="datasink" name="Data Sink" id="d9cc1e83-5895-4cab-b34c-6f95e09e1096">
        <con:settings/>
        <con:config xsi:type="con:DataSinkStep" xmlns:xsi="http://www.w3.org/2001/XMLSchema-instance">
          <con:dataSink type="Excel">
            <con:configuration>
              <file/>
              <outfile>E:/Book1.xlsx</outfile>
              <worksheet>sheet1</worksheet>
              <cell>h2</cell>
              <evaluateFormulas>false</evaluateFormulas>
              <append>false</append>
            </con:configuration>
          </con:dataSink>
          <con:properties>
            <con:property>
              <con:name>ID</con:name>
              <con:value>${POST_API#Response}</con:value>
            </con:property>
          </con:properties>
        </con:config>
      </con:testStep>
      <con:testStep type="restrequest" name="put_API" id="18730c46-4865-4c7f-b5fd-b01177e5ba71">
        <con:settings/>
        <con:config service="https://petstore.swagger.io" resourcePath="/v2/user/{username}" methodName="Method 4" xsi:type="con:RestRequestStep" xmlns:xsi="http://www.w3.org/2001/XMLSchema-instance">
          <con:restRequest name="put_API" id="6d1b006e-993c-494a-922a-81c39bc41aa8" mediaType="application/json" postQueryString="false">
            <con:settings>
              <con:setting id="com.eviware.soapui.impl.wsdl.WsdlRequest@request-headers">&lt;xml-fragment/></con:setting>
            </con:settings>
            <con:endpoint>https://petstore.swagger.io</con:endpoint>
            <con:request>{
  "id": 0,
  "username": "${Data Source#username}",
  "firstName": "${Data Source#firstname}",
  "lastName": "${Data Source#lastname}",
  "email": "${Data Source#email}",
  "password": "${Data Source#validnum}",
  "phone": "${Data Source#phoennum}",
  "userStatus": 0
}</con:request>
            <con:originalUri>https://petstore.swagger.io/v2/user/username</con:originalUri>
            <con:credentials>
              <con:selectedAuthProfile>No Authorization</con:selectedAuthProfile>
              <con:authType>No Authorization</con:authType>
            </con:credentials>
            <con:jmsConfig JMSDeliveryMode="PERSISTENT"/>
            <con:parameters>
              <con:entry key="username" value="${Data Source#password}"/>
            </con:parameters>
          </con:restRequest>
        </con:config>
      </con:testStep>
      <con:testStep type="restrequest" name="delete_API" id="b10480c0-5398-434f-966e-15ae87f77915">
        <con:settings/>
        <con:config service="https://petstore.swagger.io" resourcePath="/v2/user/{username}" methodName="Method 2" xsi:type="con:RestRequestStep" xmlns:xsi="http://www.w3.org/2001/XMLSchema-instance">
          <con:restRequest name="delete_API" id="352a4d42-1180-434b-9c58-33fbc0f3597c" mediaType="application/json" postQueryString="false">
            <con:settings>
              <con:setting id="com.eviware.soapui.impl.wsdl.WsdlRequest@request-headers">&lt;xml-fragment/></con:setting>
            </con:settings>
            <con:endpoint>https://petstore.swagger.io</con:endpoint>
            <con:request/>
            <con:originalUri>https://petstore.swagger.io/v2/user/username</con:originalUri>
            <con:credentials>
              <con:selectedAuthProfile>No Authorization</con:selectedAuthProfile>
              <con:authType>No Authorization</con:authType>
            </con:credentials>
            <con:jmsConfig JMSDeliveryMode="PERSISTENT"/>
            <con:parameters>
              <con:entry key="username" value="${Data Source#username}"/>
            </con:parameters>
          </con:restRequest>
        </con:config>
      </con:testStep>
      <con:testStep type="datasourceloop" name="Data Source Loop" id="f903b0e7-3be5-4134-8b70-4b2fda27b7db">
        <con:settings/>
        <con:config>
          <dataSourceStep>Data Source</dataSourceStep>
          <targetStep>POST_API</targetStep>
          <discardResults>true</discardResults>
        </con:config>
      </con:testStep>
      <con:properties/>
      <con:reportParameters/>
      <con:breakPoints>
        <con:testStepId>4f3e129b-d2b7-492f-8c46-8a66233dece3</con:testStepId>
        <con:status>NONE</con:status>
        <con:properties/>
      </con:breakPoints>
      <con:breakPoints>
        <con:testStepId>cb5c34f1-8edf-430c-92f9-870fc943a6d2</con:testStepId>
        <con:status>NONE</con:status>
        <con:properties/>
      </con:breakPoints>
      <con:breakPoints>
        <con:testStepId>5d4ec8bb-31dd-4700-83b4-cd0a8378ae0a</con:testStepId>
        <con:status>NONE</con:status>
        <con:properties/>
      </con:breakPoints>
      <con:breakPoints>
        <con:testStepId>d9cc1e83-5895-4cab-b34c-6f95e09e1096</con:testStepId>
        <con:status>NONE</con:status>
        <con:properties/>
      </con:breakPoints>
      <con:breakPoints>
        <con:testStepId>7cebd24a-6760-4112-a3d3-352d36a3f0d6</con:testStepId>
        <con:status>NONE</con:status>
        <con:properties/>
      </con:breakPoints>
      <con:breakPoints>
        <con:testStepId>b10480c0-5398-434f-966e-15ae87f77915</con:testStepId>
        <con:status>NONE</con:status>
        <con:properties/>
      </con:breakPoints>
      <con:breakPoints>
        <con:testStepId>18730c46-4865-4c7f-b5fd-b01177e5ba71</con:testStepId>
        <con:status>NONE</con:status>
        <con:properties/>
      </con:breakPoints>
    </con:testCase>
    <con:properties/>
    <con:reportParameters/>
  </con:testSuite>
  <con:savedRecentRuns>1</con:savedRecentRuns>
  <con:requirements/>
  <con:properties/>
  <con:wssContainer/>
  <con:databaseConnectionContainer/>
  <con:jmsConnectionContainer/>
  <con:oAuth2ProfileContainer/>
  <con:oAuth1ProfileContainer/>
  <con:reporting>
    <con:reportTemplates/>
    <con:xmlTemplates/>
    <con:xmlTemplates/>
    <con:parameters/>
    <con:parameters/>
  </con:reporting>
  <con:reporting/>
  <con:eventHandlers type="RequestFilter.filterRequest" name="RequestFilter.filterRequest">
    <con:script>// Sample event script to add custom HTTP header to all outgoing REST, SOAP and HTTP(S) calls
// This code is often used for adding custom authentication to ReadyAPI functional tests

// If hardcoding the token, uncomment and change line 5
// token = '4567'

// If your token is parameterized in Project level custom property, uncomment line 8
// token = request.parent.testCase.testSuite.project.getProperty('auth_token').getValue()

// To modify all outgoing calls, remove comments from lines 11 to 16
// headers = request.requestHeaders
// if (headers.containsKey('auth_token2') == false) {
//   headers.put('auth_token2', token)
//   request.requestHeaders = headers
// }</con:script>
  </con:eventHandlers>
  <con:eventHandlers type="TestRunListener.afterStep" name="TestRunListener.afterStep">
    <con:script>// Save all test step results into files
// Change the directory path in line 5 to a location where you want to store details
// then uncomment lines 5 to 10

// filePath = 'C:\\tempOutputDirectory\\'
// fos = new java.io.FileOutputStream(filePath + testStepResult.testStep.label + '.txt', true)
// pw = new java.io.PrintWriter(fos)
// testStepResult.writeTo(pw)
// pw.close()
// fos.close()</con:script>
  </con:eventHandlers>
  <con:authRepository/>
  <con:tags/>
</con:soapui-project